parsegument/BaseGroup.py
parsegument/Command.py
parsegument/CommandGroup.py
parsegument/Node.py
parsegument/Parameters.py
parsegument/Parsegumenter.py
parsegument/__init__.py
parsegument/error.py
parsegument/formatting.py
parsegument/decorators/__init__.py
parsegument/decorators/parameters.py
parsegument/types/ArgDict.py
parsegument/types/__init__.py
parsegument/utils/__init__.py
parsegument/utils/convert_params.py
parsegument/utils/parser.py
parsegument-0.3.1.dist-info/licenses/LICENSE.txt
parsegument-0.3.1.dist-info/METADATA
parsegument-0.3.1.dist-info/WHEEL
parsegument-0.3.1.dist-info/top_level.txt
parsegument-0.3.1.dist-info/RECORD
