Metadata-Version: 2.4
Name: parsegument
Version: 0.3.1
Summary: Parsegument is a python package for creating CLIs and adding text-based function execution for other applications!.
Author-email: Ryan Studio <ryanstudiobusiness@gmail.com>
Project-URL: Repository, https://github.com/RyanStudioo/Parsegument
Keywords: parsegument,parser,argument parse,parse,CLI,command line interface
Requires-Python: >=3.11
License-File: LICENSE.txt
Dynamic: license-file
